{
    "habitat_codes": {
      "ACID FLUSH": {"type": "ignore", "density": 0},
      "ACID FLUSH & SCATTERED SCRUB": {"type": "scrub", "density": 5},
      "ACID GRASSLAND": {"type": "ignore", "density": 0},
      "ACID GRASSLAND & SCATTERED GORSE SCRUB MOSAIC": {"type": "scrub", "density": 6},
      "ACID GRASSLAND WITH SCATTERED SCRUB WOODY MOSAICS": {"type": "scrub", "density": 5},
      "BASE RICH FEN": {"type": "ignore", "density": 0},
      "BASE RICH FEN MOSIAC": {"type": "ignore", "density": 0},
      "BLANKET BOG": {"type": "ignore", "density": 0},
      "BLANKET BOG & ACID GRASSLAND": {"type": "ignore", "density": 0},
      "BLANKET BOG & DRY HEATH": {"type": "ignore", "density": 0},
      "BLANKET BOG & MIRE": {"type": "ignore", "density": 0},
      "BLANKET BOG & WET WOODLAND": {"type": "ignore", "density": 0},
      "BLANKET BOG & WILLOW SCRUB": {"type": "scrub", "density": 7},
      "BLANKET BOG SCATTERED SCRUB MOSAIC": {"type": "scrub", "density": 5},
      "BLANKET BOG WITH SCATTERED SCRUB WOODY MOSAICS": {"type": "scrub", "density": 6},
      "BROADLEAVED WOODLAND": {"type": "ignore", "density": 0},
      "BROADLEAVED WOODLAND & SCRUB": {"type": "mixed", "density": 7},
      "BROADLEAVED WOODLAND SCATTERED SCRUB": {"type": "mixed", "density": 6},
      "BROADLEAVED/WET WOODLAND": {"type": "ignore", "density": 0},
      "CLOUGH SCRUB/WOODLAND": {"type": "scrub", "density": 7},
      "CLOUGH WOODLAND": {"type": "ignore", "density": 0},
      "CONIFER WOODLAND": {"type": "ignore", "density": 0},
      "DENSE & SCATTERED SCRUB MOSIAC": {"type": "scrub", "density": 8},
      "DENSE BRACKEN": {"type": "ignore", "density": 0},
      "DENSE BRACKEN & SCRUB": {"type": "scrub", "density": 6},
      "DRY HEATH": {"type": "ignore", "density": 0},
      "DRY HEATH & SCRUB MOSAIC": {"type": "scrub", "density": 6},
      "DRY HEATH & ACID GRASSLAND MOSAIC": {"type": "ignore", "density": 0},
      "DRY HEATH & SCATTERED SCRUB": {"type": "scrub", "density": 5},
      "DRY HEATH & SCRUB/TREE MOSAIC": {"type": "mixed", "density": 5},
      "DRY HEATH & WET HEATH": {"type": "ignore", "density": 0},
      "DRY HEATH ACID GRASSLAND & SCATTERED SCRUB MOSAICS": {"type": "scrub", "density": 5},
      "DRY HEATH FLUSH WITH SCATTERED SCRUB MOSAICS": {"type": "scrub", "density": 5},
      "DRY HEATH WITH SCATTERED SCRUB WOODY MOSAICS": {"type": "scrub", "density": 6},
      "DRY HEATH/WET HEATH & BLANKET BOG MOSAIC": {"type": "ignore", "density": 0},
      "DRY WOODLAND": {"type": "ignore", "density": 0},
      "FLUSH": {"type": "ignore", "density": 0},
      "FLUSH & WILLOW SCRUB": {"type": "scrub", "density": 7},
      "FLUSH WITH SCATTERED SCRUB WOODY MOSAICS": {"type": "scrub", "density": 5},
      "GORSE SCRUB": {"type": "scrub", "density": 8},
      "MARSHY /ACID /NEUTRAL  -MOSAIC SPECIES RICH GRASSLANDS": {"type": "ignore", "density": 0},
      "MARSHY /ACID /NEUTRAL  -MOSAIC SPECIES RICH GRASSLANDS WITH SCATTERED SCRUB WOODY MOSAICS": {"type": "scrub", "density": 6},
      "MARSHY GRASSLAND": {"type": "ignore", "density": 0},
      "MIXED WOODLAND": {"type": "ignore", "density": 0},
      "MOSAIC SPECIES RICH WETTER GRASSLAND & WILLOW SCRUB": {"type": "scrub", "density": 7},
      "RIPARIAN CORRIDOR WITH SCRUB WOODY MOSAICS": {"type": "scrub", "density": 7},
      "SCATTERED SCRUB": {"type": "scrub", "density": 5},
      "SCATTERED SCRUB SPECIES RICH GRASSLAND MOSAIC": {"type": "scrub", "density": 6},
      "SCRUB": {"type": "scrub", "density": 8},
      "SCRUB WOODLAND": {"type": "scrub", "density": 9},
      "SCRUB WOODLAND DRY HEATH MOSAIC": {"type": "scrub", "density": 7},
      "SPECIES RICH GRASSLAND & DRY HEATH": {"type": "ignore", "density": 0},
      "SPECIES RICH GRASSLAND SCRUB MOSAIC": {"type": "scrub", "density": 6},
      "TALL HERB": {"type": "ignore", "density": 0},
      "WET GRASSLAND WITH SCATTERED SCRUB": {"type": "scrub", "density": 5},
      "WET HEATH": {"type": "ignore", "density": 0},
      "WET HEATH & DRY HEATH": {"type": "ignore", "density": 0},
      "WET HEATH & SCATTERED SCRUB": {"type": "scrub", "density": 5},
      "WET HEATH WITH SCATTERED SCRUB WOODY MOSAICS": {"type": "scrub", "density": 6},
      "WET WOODLAND": {"type": "ignore", "density": 0},
      "WET WOODLAND & MIRE": {"type": "ignore", "density": 0},
      "WET WOODLAND & WETLAND": {"type": "ignore", "density": 0},
      "WILLOW SCRUB": {"type": "scrub", "density": 9},
      "WOOD PASTURE": {"type": "wood_pasture", "density": 3}
    }
  }
  